pySpeedy/Setup.py
pySpeedy/__init__.py
pySpeedy/pySpeedyAPI.dll
pySpeedy/pySpeedyAPI_64.dll
pySpeedy/pySpeedyAPI_64.so
pySpeedy/spdOrderAPI.cp311-win_amd64.pyd
pySpeedy/spdOrderAPI.cpython-36m-x86_64-linux-gnu.so
pySpeedy/spdOrderAPI.py
pySpeedy/spdQuoteAPI.cp311-win_amd64.pyd
pySpeedy/spdQuoteAPI.py
pySpeedy/Temp/Contract.dat
pySpeedy/Temp/FUT.0619054640.ini
pySpeedy/Temp/FUT_C030.ini
pySpeedy/Temp/FUT_C030CR.ini
pySpeedy/Temp/FUT_R010.ini
pySpeedy/Temp/FUT_R020.ini
pySpeedy/Temp/OPT_C030.ini
pySpeedy/Temp/OPT_C030CR.ini
pySpeedy/Temp/OPT_C030M.ini
pySpeedy/Temp/OPT_C030QCR.ini
pySpeedy/Temp/OPT_R010.ini
pySpeedy/Temp/OPT_R020.ini
pySpeedy/Temp/OPT_R070.ini
pySpeedy/Temp/OPT_R080.ini
pySpeedy/Temp/OPT_R090.ini
pySpeedy/Temp/OPT_R100.ini
pySpeedy/Temp/OTC_E010.ini
pySpeedy/Temp/OTC_E010Ex.ini
pySpeedy/Temp/OTC_E020.ini
pySpeedy/Temp/OTC_E020Ex.ini
pySpeedy/Temp/OTC_Ex010.ini
pySpeedy/Temp/OTC_Ex010Ex.ini
pySpeedy/Temp/OTC_Ex020.ini
pySpeedy/Temp/OTC_Ex020Ex.ini
pySpeedy/Temp/OTC_O010.ini
pySpeedy/Temp/OTC_O010Ex.ini
pySpeedy/Temp/OTC_O020.ini
pySpeedy/Temp/OTC_O020Ex.ini
pySpeedy/Temp/OTC_P010.ini
pySpeedy/Temp/OTC_P010Ex.ini
pySpeedy/Temp/OTC_P020.ini
pySpeedy/Temp/OTC_P020Ex.ini
pySpeedy/Temp/OTC_R030.ini
pySpeedy/Temp/OTC_R030Ex.ini
pySpeedy/Temp/OTC_T010.ini
pySpeedy/Temp/OTC_T020.ini
pySpeedy/Temp/OTC_T020Ex.ini
pySpeedy/Temp/OTC_V010.ini
pySpeedy/Temp/OTC_V010Ex.ini
pySpeedy/Temp/OTC_V020.ini
pySpeedy/Temp/OTC_V020Ex.ini
pySpeedy/Temp/TAIFEXErrorCH.ini
pySpeedy/Temp/TAIFEXErrorEN.ini
pySpeedy/Temp/TSE_A010.ini
pySpeedy/Temp/TSE_A010Ex.ini
pySpeedy/Temp/TSE_A020.ini
pySpeedy/Temp/TSE_A020Ex.ini
pySpeedy/Temp/TSE_E010.ini
pySpeedy/Temp/TSE_E010Ex.ini
pySpeedy/Temp/TSE_E020.ini
pySpeedy/Temp/TSE_E020Ex.ini
pySpeedy/Temp/TSE_Ex010.ini
pySpeedy/Temp/TSE_Ex010Ex.ini
pySpeedy/Temp/TSE_Ex020.ini
pySpeedy/Temp/TSE_Ex020Ex.ini
pySpeedy/Temp/TSE_O010.ini
pySpeedy/Temp/TSE_O010Ex.ini
pySpeedy/Temp/TSE_O020.ini
pySpeedy/Temp/TSE_O020Ex.ini
pySpeedy/Temp/TSE_P010.ini
pySpeedy-2.5.0.10.dist-info/LICENSE
pySpeedy-2.5.0.10.dist-info/METADATA
pySpeedy-2.5.0.10.dist-info/WHEEL
pySpeedy-2.5.0.10.dist-info/top_level.txt
pySpeedy-2.5.0.10.dist-info/RECORD
