Metadata-Version: 2.1
Name: pySpeedy
Version: 2.5.0.10
Summary: Speedy Python API
Author: MDBS
Author-email: simon@mdbs.com.tw
Keywords: Speedy StarWave
Classifier: Development Status :: 5 - Production/Stable
Classifier: Intended Audience :: Developers
Classifier: Programming Language :: Python :: 3
Classifier: License :: OSI Approved :: MIT License
Classifier: Operating System :: OS Independent
License-File: LICENSE
